python_slimta_lookup-0.2.1-py2.7-nspkg.pth
python_slimta_lookup-0.2.1.dist-info/DESCRIPTION.rst
python_slimta_lookup-0.2.1.dist-info/METADATA
python_slimta_lookup-0.2.1.dist-info/RECORD
python_slimta_lookup-0.2.1.dist-info/WHEEL
python_slimta_lookup-0.2.1.dist-info/metadata.json
python_slimta_lookup-0.2.1.dist-info/namespace_packages.txt
python_slimta_lookup-0.2.1.dist-info/top_level.txt
slimta/lookup/__init__.py
slimta/lookup/auth.py
slimta/lookup/policy.py
slimta/lookup/drivers/__init__.py
slimta/lookup/drivers/dbapi2.py
slimta/lookup/drivers/dict.py
slimta/lookup/drivers/redis.py
slimta/lookup/drivers/regex.py
